pinference/__init__.py
pinference/api_manager.py
pinference/apis/__init__.py
pinference/apis/default/__init__.py
pinference/apis/default/index.py
pinference/apis/default/v1/__init__.py
pinference/apis/default/v1/config.py
pinference/apis/default/v1/models.py
pinference/apis/default/v1/parsers.py
pinference/apis/default/v1/routers/__init__.py
pinference/apis/default/v1/routers/basic.py
pinference/apis/default/v1/routers/management.py
pinference/apis/default/v1/routers/metadata.py
pinference/apis/default/v1/routers/predict.py
pinference/apis/kserve/__init__.py
pinference/apis/kserve/v1/__init__.py
pinference/apis/kserve/v1/config.py
pinference/apis/kserve/v1/models.py
pinference/apis/kserve/v1/parsers.py
pinference/apis/kserve/v1/routers/__init__.py
pinference/apis/kserve/v1/routers/metadata.py
pinference/apis/kserve/v1/routers/predict.py
pinference/apis/kserve/v2/__init__.py
pinference/apis/kserve/v2/config.py
pinference/apis/kserve/v2/models.py
pinference/apis/kserve/v2/parsers.py
pinference/apis/kserve/v2/routers/__init__.py
pinference/apis/kserve/v2/routers/metadata.py
pinference/apis/kserve/v2/routers/predict.py
pinference/app.py
pinference/context.py
pinference/handlers.py
pinference/model_manager.py
pinference/repository.py
pinference-0.1.0b1.dist-info/LICENSE
pinference-0.1.0b1.dist-info/WHEEL
pinference-0.1.0b1.dist-info/METADATA
pinference-0.1.0b1.dist-info/RECORD
