Metadata-Version: 2.1
Name: pinference
Version: 0.1.0b1
Summary: Aims to be the Simplest Machine Learning Model Inference Server
Home-page: https://pinferencia.underneathall.app
License: Apache-2.0 License
Keywords: Machine Learning,Inference,Serve
Author: Jiuhe Wang
Author-email: wjiuhe@gmail.com
Requires-Python: >=3.6.2,<4.0.0
Classifier: Development Status :: 3 - Alpha
Classifier: Environment :: GPU
Classifier: Environment :: Web Environment
Classifier: Framework :: FastAPI
Classifier: Intended Audience :: Developers
Classifier: Intended Audience :: Information Technology
Classifier: Intended Audience :: Science/Research
Classifier: License :: OSI Approved :: Apache Software License
Classifier: License :: Other/Proprietary License
Classifier: Operating System :: OS Independent
Classifier: Programming Language :: Python :: 3
Classifier: Programming Language :: Python :: 3 :: Only
Classifier: Programming Language :: Python :: 3.10
Classifier: Programming Language :: Python :: 3.6
Classifier: Programming Language :: Python :: 3.7
Classifier: Programming Language :: Python :: 3.8
Classifier: Programming Language :: Python :: 3.9
Classifier: Topic :: Internet :: WWW/HTTP :: HTTP Servers
Classifier: Topic :: Scientific/Engineering :: Information Analysis
Classifier: Topic :: Software Development :: Libraries :: Python Modules
Classifier: Typing :: Typed
Provides-Extra: uvicorn
Requires-Dist: fastapi (>=0.75.1,<0.76.0)
Requires-Dist: numpy (>=1.19.5,<2.0.0); python_version >= "3.6" and python_version < "3.7"
Requires-Dist: numpy (>=1.20.3,<2.0.0); python_version >= "3.7" and python_version < "3.8"
Requires-Dist: numpy (>=1.22.3,<2.0.0); python_version >= "3.8" and python_version < "4.0"
Requires-Dist: uvicorn[standard] (>=0.16.0,<0.17.0); extra == "uvicorn"
Project-URL: Repository, https://github.com/underneathall/pinferencia
